scrapy_crawlera/__init__.py
scrapy_crawlera/middleware.py
scrapy_crawlera/utils.py
scrapy_crawlera-1.7.1.dist-info/METADATA
scrapy_crawlera-1.7.1.dist-info/WHEEL
scrapy_crawlera-1.7.1.dist-info/top_level.txt
scrapy_crawlera-1.7.1.dist-info/RECORD
