Metadata-Version: 2.1
Name: scrapy-crawlera
Version: 1.7.1
Summary: Crawlera middleware for Scrapy
Home-page: https://github.com/scrapy-plugins/scrapy-crawlera
Author: Scrapinghub
Author-email: opensource@scrapinghub.com
Maintainer: Raul Gallegos
Maintainer-email: raul.ogh@gmail.com
License: BSD
Platform: Any
Classifier: Development Status :: 5 - Production/Stable
Classifier: License :: OSI Approved :: BSD License
Classifier: Operating System :: OS Independent
Classifier: Programming Language :: Python
Classifier: Programming Language :: Python :: 2
Classifier: Programming Language :: Python :: 2.7
Classifier: Programming Language :: Python :: 3
Classifier: Programming Language :: Python :: 3.4
Classifier: Programming Language :: Python :: 3.5
Classifier: Programming Language :: Python :: 3.6
Classifier: Framework :: Scrapy
Classifier: Intended Audience :: Developers
Classifier: Topic :: Internet :: WWW/HTTP
Classifier: Topic :: Internet :: Proxy Servers
Classifier: Topic :: Software Development :: Libraries :: Application Frameworks
Classifier: Topic :: Software Development :: Libraries :: Python Modules
Requires-Dist: scrapy (>=1.0.0)
Requires-Dist: six
Requires-Dist: w3lib
